jupyter_beeper/Beeper.py
jupyter_beeper/__init__.py
Jupyter_Beeper-1.0.3.dist-info/LICENSE
Jupyter_Beeper-1.0.3.dist-info/METADATA
Jupyter_Beeper-1.0.3.dist-info/WHEEL
Jupyter_Beeper-1.0.3.dist-info/top_level.txt
Jupyter_Beeper-1.0.3.dist-info/RECORD
