Metadata-Version: 2.1
Name: Jupyter-Beeper
Version: 1.0.3
Summary: A beep generator for Jupyter Notebooks (and Jupyter-Lab) that doesn't display an audio reproduction widget.
Home-page: https://github.com/jeanyvesb9/Jupyter-Beeper
Author: Jean Yves Beaucamp (@jeanyvesb9)
Author-email: jeanyvesb9@me.com
License: UNKNOWN
Keywords: beep beeper sounds ipython jupyter
Platform: UNKNOWN
Requires-Dist: ipython
Requires-Dist: numpy
